foliant/preprocessors/dbmldoc/__init__.py
foliant/preprocessors/dbmldoc/dbmldoc.py
foliant/preprocessors/dbmldoc/template/dbml.j2
foliant/preprocessors/dbmldoc/template/scheme.j2
foliantcontrib.dbmldoc-0.3.4.dist-info/LICENSE
foliantcontrib.dbmldoc-0.3.4.dist-info/METADATA
foliantcontrib.dbmldoc-0.3.4.dist-info/WHEEL
foliantcontrib.dbmldoc-0.3.4.dist-info/top_level.txt
foliantcontrib.dbmldoc-0.3.4.dist-info/RECORD
