Metadata-Version: 2.1
Name: foliantcontrib.dbmldoc
Version: 0.3.4
Summary: Documentation generator for DBML specification format
Home-page: UNKNOWN
Author: Daniil Minukhin
Author-email: ddddsa@gmail.com
License: MIT
Platform: any
Classifier: Development Status :: 5 - Production/Stable
Classifier: Environment :: Console
Classifier: Intended Audience :: Developers
Classifier: License :: OSI Approved :: MIT License
Classifier: Operating System :: OS Independent
Classifier: Programming Language :: Python
Classifier: Topic :: Documentation
Classifier: Topic :: Utilities
License-File: LICENSE
Requires-Dist: foliant (>=1.0.5)
Requires-Dist: jinja2
Requires-Dist: pydbml (>=1.0.6)
Requires-Dist: foliantcontrib.utils (>=1.0.2)
